gsfpy/GSF_POSITION.py
gsfpy/GSF_POSITION_OFFSETS.py
gsfpy/__init__.py
gsfpy/bindings.py
gsfpy/constants.py
gsfpy/enums.py
gsfpy/gsfAttitude.py
gsfpy/gsfBRBIntensity.py
gsfpy/gsfComment.py
gsfpy/gsfDataID.py
gsfpy/gsfHVNavigationError.py
gsfpy/gsfHeader.py
gsfpy/gsfHistory.py
gsfpy/gsfMBOffsets.py
gsfpy/gsfMBParams.py
gsfpy/gsfNavigationError.py
gsfpy/gsfProcessingParameters.py
gsfpy/gsfRecords.py
gsfpy/gsfSBSensorSpecific.py
gsfpy/gsfSVP.py
gsfpy/gsfScaleFactors.py
gsfpy/gsfSensorParameters.py
gsfpy/gsfSensorSpecific.py
gsfpy/gsfSingleBeamPing.py
gsfpy/gsfSwathBathyPing.py
gsfpy/gsfSwathBathySummary.py
gsfpy/timespec.py
gsfpy3_08/GSF_POSITION.py
gsfpy3_08/GSF_POSITION_OFFSETS.py
gsfpy3_08/__init__.py
gsfpy3_08/bindings.py
gsfpy3_08/constants.py
gsfpy3_08/enums.py
gsfpy3_08/gsfAttitude.py
gsfpy3_08/gsfBRBIntensity.py
gsfpy3_08/gsfComment.py
gsfpy3_08/gsfDataID.py
gsfpy3_08/gsfHVNavigationError.py
gsfpy3_08/gsfHeader.py
gsfpy3_08/gsfHistory.py
gsfpy3_08/gsfMBOffsets.py
gsfpy3_08/gsfMBParams.py
gsfpy3_08/gsfNavigationError.py
gsfpy3_08/gsfProcessingParameters.py
gsfpy3_08/gsfRecords.py
gsfpy3_08/gsfSBSensorSpecific.py
gsfpy3_08/gsfSVP.py
gsfpy3_08/gsfScaleFactors.py
gsfpy3_08/gsfSensorParameters.py
gsfpy3_08/gsfSensorSpecific.py
gsfpy3_08/gsfSingleBeamPing.py
gsfpy3_08/gsfSwathBathyPing.py
gsfpy3_08/gsfSwathBathySummary.py
gsfpy3_08/libgsf/libgsf03-08.so
gsfpy3_08/libgsf/libgsf_LICENSE.md
gsfpy3_08/timespec.py
gsfpy3_09/GSF_POSITION.py
gsfpy3_09/GSF_POSITION_OFFSETS.py
gsfpy3_09/__init__.py
gsfpy3_09/bindings.py
gsfpy3_09/constants.py
gsfpy3_09/enums.py
gsfpy3_09/gsfAttitude.py
gsfpy3_09/gsfBRBIntensity.py
gsfpy3_09/gsfComment.py
gsfpy3_09/gsfDataID.py
gsfpy3_09/gsfHVNavigationError.py
gsfpy3_09/gsfHeader.py
gsfpy3_09/gsfHistory.py
gsfpy3_09/gsfMBOffsets.py
gsfpy3_09/gsfMBParams.py
gsfpy3_09/gsfNavigationError.py
gsfpy3_09/gsfProcessingParameters.py
gsfpy3_09/gsfRecords.py
gsfpy3_09/gsfSBSensorSpecific.py
gsfpy3_09/gsfSVP.py
gsfpy3_09/gsfScaleFactors.py
gsfpy-2.0.0.dist-info/LICENSE
gsfpy-2.0.0.dist-info/WHEEL
gsfpy-2.0.0.dist-info/METADATA
gsfpy-2.0.0.dist-info/RECORD
