Metadata-Version: 2.1
Name: gsfpy
Version: 2.0.0
Summary: Python wrapper for the C implementation of the Generic Sensor Format library.
Home-page: https://github.com/UKHO/gsfpy
License: MIT
Keywords: bathymetry,gsf,libgsf
Author: UK Hydrographic Office
Author-email: datascienceandengineering@ukho.gov.uk
Requires-Python: >=3.6,<4.0
Classifier: Development Status :: 4 - Beta
Classifier: Intended Audience :: Developers
Classifier: Intended Audience :: Science/Research
Classifier: License :: OSI Approved :: MIT License
Classifier: Natural Language :: English
Classifier: Programming Language :: Python :: 3
Classifier: Programming Language :: Python :: 3.6
Classifier: Programming Language :: Python :: 3.7
Classifier: Programming Language :: Python :: 3.8
Project-URL: Repository, https://github.com/UKHO/gsfpy
